bgpt/__init__.py
bgpt/main.py
bgpt-0.1.1.dist-info/licenses/LICENSE
bgpt-0.1.1.dist-info/METADATA
bgpt-0.1.1.dist-info/WHEEL
bgpt-0.1.1.dist-info/entry_points.txt
bgpt-0.1.1.dist-info/top_level.txt
bgpt-0.1.1.dist-info/RECORD
