Metadata-Version: 2.4
Name: bgpt
Version: 0.1.1
Summary: A CLI tool to convert natural language to bash commands using OpenAI.
Author-email: Jonathan Radas <jonathan.radas@uni.muenster.de>
License: MIT
Project-URL: Homepage, https://github.com/jorado/bgpt
Project-URL: Issues, https://github.com/jorado/bgpt/issues
Classifier: Programming Language :: Python :: 3
Classifier: License :: OSI Approved :: MIT License
Classifier: Operating System :: OS Independent
Classifier: Environment :: Console
Classifier: Environment :: Console
Classifier: Intended Audience :: Developers
Classifier: Topic :: Utilities
Requires-Python: >=3.8
License-File: LICENSE
Requires-Dist: openai>=1.0
Provides-Extra: dev
Requires-Dist: pytest; extra == "dev"
Requires-Dist: pytest-mock; extra == "dev"
Dynamic: license-file
